oftop/__init__.py
oftop/main.py
oftop-0.1.4.dist-info/METADATA
oftop-0.1.4.dist-info/WHEEL
oftop-0.1.4.dist-info/entry_points.txt
oftop-0.1.4.dist-info/top_level.txt
oftop-0.1.4.dist-info/RECORD
