Metadata-Version: 2.1
Name: oftop
Version: 0.1.4
Summary: Open File Top
Home-page: https://github.com/manuels/oftop
Author: M. Schölling
Author-email: manuel.schoelling@gmx.de
License: UNKNOWN
Platform: UNKNOWN
Classifier: Programming Language :: Python :: 3
Classifier: License :: OSI Approved :: GNU General Public License v3 or later (GPLv3+)
Requires-Dist: psutil
Requires-Dist: pathlib
